asyncbing/__init__.py
asyncbing/exceptions.py
asyncbing/search.py
asyncbing/searchresponse.py
asyncbing/searchresult.py
asyncbing/translate.py
asyncbing/translateresponse.py
asyncbing-2.0.3.dist-info/LICENSE
asyncbing-2.0.3.dist-info/METADATA
asyncbing-2.0.3.dist-info/WHEEL
asyncbing-2.0.3.dist-info/top_level.txt
asyncbing-2.0.3.dist-info/RECORD
