Metadata-Version: 2.1
Name: asyncbing
Version: 2.0.3
Summary: A api wrapper for the bing apis.
Home-page: https://github.com/TennisBowling/asyncbing
Author: TennisBowling
Author-email: tennisbowling@tennisbowling.com
License: LICENSE.md
Platform: UNKNOWN
License-File: LICENSE
Requires-Dist: aiohttp
Requires-Dist: asyncio
